hanazeder_server/BaseServer.py
hanazeder_server/MqttClient.py
hanazeder_server/__init__.py
hanazeder_server/mqtt.py
hanazeder_server-1.1.1.dist-info/LICENSE
hanazeder_server-1.1.1.dist-info/WHEEL
hanazeder_server-1.1.1.dist-info/METADATA
hanazeder_server-1.1.1.dist-info/RECORD
